casta/__init__.py
casta/__main__.py
casta/example.py
casta/features.py
casta/hmm_functions.py
casta/main.py
casta/plot.py
casta/results.py
casta/utils.py
casta/data/__init__.py
casta/data/example_track.csv
casta/data/model_4.pkl
casta/ml_old/MLGeneral.py
casta/ml_old/RandomWalkSims.py
casta/ml_old/my_Fingerprint_feat_gen.py
casta-0.1.0.dist-info/licenses/LICENSE
casta-0.1.0.dist-info/METADATA
casta-0.1.0.dist-info/WHEEL
casta-0.1.0.dist-info/entry_points.txt
casta-0.1.0.dist-info/top_level.txt
casta-0.1.0.dist-info/RECORD
