Metadata-Version: 2.4
Name: casta
Version: 0.1.0
Summary: Calculate spatial transient arrests
Author-email: Michelle von Arx <michelle.vonarx@tum.de>, Philip Schulz <philip.schulz@outlook.com>
License: MIT License
Project-URL: Homepage, https://github.com/NanoSignalingLab/photochromic-reversion/
Classifier: License :: OSI Approved :: MIT License
Classifier: Programming Language :: Python
Classifier: Programming Language :: Python :: 3
Requires-Python: >=3.10
License-File: LICENSE
Requires-Dist: numpy<=1.26.4
Requires-Dist: pandas>=2.2.3
Requires-Dist: scipy>=1.15.0
Requires-Dist: matplotlib>=3.10.0
Requires-Dist: seaborn>=0.13.2
Requires-Dist: scikit-learn>=1.6.1
Requires-Dist: hmmlearn>=0.3.3
Requires-Dist: tqdm>=4.67.1
Requires-Dist: shapely>=2.0.6
Requires-Dist: xlsxwriter>=3.2.3
Dynamic: license-file
